swagger_merger/__init__.py
swagger_merger/src/__init__.py
swagger_merger/src/cli.py
swagger_merger/src/swagger_merger.py
swagger_merger-1.2.0.dist-info/LICENSE
swagger_merger-1.2.0.dist-info/METADATA
swagger_merger-1.2.0.dist-info/WHEEL
swagger_merger-1.2.0.dist-info/entry_points.txt
swagger_merger-1.2.0.dist-info/top_level.txt
swagger_merger-1.2.0.dist-info/RECORD
