Metadata-Version: 2.1
Name: swagger-merger
Version: 1.2.0
Summary: swagger merger python package
Home-page: https://github.com/ostadkarteam/swagger-merger
Author: Sina Mehrabi
License: UNKNOWN
Platform: UNKNOWN
Classifier: Programming Language :: Python :: 3
Classifier: License :: OSI Approved :: MIT License
Classifier: Operating System :: OS Independent
Requires-Python: >=3.6
Requires-Dist: deepmerge
Requires-Dist: PyYAML
